nhs_aws_helpers/__init__.py
nhs_aws_helpers/async_s3_object_reader.py
nhs_aws_helpers/async_s3_object_writer.py
nhs_aws_helpers/common.py
nhs_aws_helpers/dynamodb_model_store/__init__.py
nhs_aws_helpers/dynamodb_model_store/base_model.py
nhs_aws_helpers/dynamodb_model_store/base_model_store.py
nhs_aws_helpers/fixtures.py
nhs_aws_helpers/py.typed
nhs_aws_helpers/s3_object_reader.py
nhs_aws_helpers/s3_object_writer.py
nhs_aws_helpers-0.7.35.dist-info/METADATA
nhs_aws_helpers-0.7.35.dist-info/WHEEL
nhs_aws_helpers-0.7.35.dist-info/licenses/LICENSE.md
nhs_aws_helpers-0.7.35.dist-info/RECORD
