Metadata-Version: 2.4
Name: nhs_aws_helpers
Version: 0.7.35
Summary: 
License: MIT
License-File: LICENSE.md
Author: spinecore
Requires-Python: >=3.9,<4.0
Classifier: License :: OSI Approved :: MIT License
Classifier: Programming Language :: Python :: 3
Classifier: Programming Language :: Python :: 3.9
Classifier: Programming Language :: Python :: 3.10
Classifier: Programming Language :: Python :: 3.11
Classifier: Programming Language :: Python :: 3.12
Classifier: Programming Language :: Python :: 3.13
Classifier: Programming Language :: Python :: 3.14
Provides-Extra: pytest
Requires-Dist: boto3 (>=1.40.43,<2.0.0)
Requires-Dist: boto3-stubs[athena,backup,ce,cloudwatch,dynamodb,ecs,events,firehose,glue,healthlake,iam,kms,lambda,logs,s3,secretsmanager,ses,sns,sqs,ssm,stepfunctions,sts] (>=1.40.43,<2.0.0)
Requires-Dist: botocore-stubs (>=1.40.33,<2.0.0)
Project-URL: Repository, https://github.com/NHSDigital/nhs-aws-helpers
